code_index_mcp/__init__.py
code_index_mcp/__main__.py
code_index_mcp/api_key_manager.py
code_index_mcp/cli.py
code_index_mcp/config_manager.py
code_index_mcp/constants.py
code_index_mcp/content_extractor.py
code_index_mcp/elasticsearch_config.py
code_index_mcp/elasticsearch_installer.py
code_index_mcp/file_change_tracker.py
code_index_mcp/file_reader.py
code_index_mcp/global_config_manager.py
code_index_mcp/ignore_patterns.py
code_index_mcp/incremental_indexer.py
code_index_mcp/lazy_loader.py
code_index_mcp/logger_config.py
code_index_mcp/lru_cache.py
code_index_mcp/memory_profiler.py
code_index_mcp/monitoring.py
code_index_mcp/optimized_project_settings.py
code_index_mcp/parallel_processor.py
code_index_mcp/performance_monitor.py
code_index_mcp/progress_tracker.py
code_index_mcp/project_settings.py
code_index_mcp/realtime_indexer.py
code_index_mcp/retry.py
code_index_mcp/search_utils.py
code_index_mcp/server.py
code_index_mcp/server.py.backup
code_index_mcp/stats_dashboard.py
code_index_mcp/system_utils.py
code_index_mcp/core_engine/__init__.py
code_index_mcp/core_engine/consolidated_tools.py
code_index_mcp/core_engine/engine.py
code_index_mcp/core_engine/interfaces.py
code_index_mcp/core_engine/local_vector_backend.py
code_index_mcp/core_engine/logger_config.py
code_index_mcp/core_engine/test_engine.py
code_index_mcp/core_engine/test_local_vector_backend.py
code_index_mcp/core_engine/tool_routers.py
code_index_mcp/core_engine/types.py
code_index_mcp/repositories/__init__.py
code_index_mcp/repositories/base.py
code_index_mcp/repositories/file_repository.py
code_index_mcp/repositories/index_repository.py
code_index_mcp/repositories/quality_metrics_repository.py
code_index_mcp/repositories/repository_factory.py
code_index_mcp/repositories/search_repository.py
code_index_mcp/search/__init__.py
code_index_mcp/search/ag.py
code_index_mcp/search/async_search.py
code_index_mcp/search/base.py
code_index_mcp/search/basic.py
code_index_mcp/search/grep.py
sc_code_indexer-2.0.1.dist-info/licenses/LICENSE
sc_code_indexer-2.0.1.dist-info/METADATA
sc_code_indexer-2.0.1.dist-info/WHEEL
sc_code_indexer-2.0.1.dist-info/entry_points.txt
sc_code_indexer-2.0.1.dist-info/top_level.txt
sc_code_indexer-2.0.1.dist-info/RECORD
