Metadata-Version: 2.4
Name: sc-code-indexer
Version: 2.0.1
Summary: Code indexing and analysis tools for LLMs using MCP
Author: scooter-lacroix
License: MIT
Project-URL: Homepage, https://github.com/scooter-lacroix/code-indexer
Project-URL: Bug Tracker, https://github.com/scooter-lacroix/code-indexer/issues
Requires-Python: <3.13,>=3.10
License-File: LICENSE
Requires-Dist: alembic>=1.16.4
Requires-Dist: aiofiles>=23.2.1
Requires-Dist: aiohttp>=3.9.0
Requires-Dist: mcp>=0.3.0
Requires-Dist: pdfminer-six>=20250506
Requires-Dist: pika>=1.3.2
Requires-Dist: psutil>=7.0.0
Requires-Dist: psycopg2-binary>=2.9.10
Requires-Dist: pytest>=8.4.1
Requires-Dist: python-docx>=1.2.0
Requires-Dist: python-json-logger>=2.0.0
Requires-Dist: pyyaml>=6.0.0
Requires-Dist: sqlalchemy>=2.0.0
Requires-Dist: lxml>=6.0.0
Requires-Dist: cffi>=1.17.0
Requires-Dist: cryptography>=45.0.0
Requires-Dist: pycparser>=2.22
Requires-Dist: six>=1.17.0
Requires-Dist: python-dateutil>=2.9.0
Requires-Dist: urllib3>=2.5.0
Requires-Dist: elastic-transport>=8.17.0
Requires-Dist: elasticsearch<9.0.0,>=8.0.0
Requires-Dist: greenlet>=3.2.0
Requires-Dist: mako>=1.3.0
Requires-Dist: markupsafe>=3.0.0
Requires-Dist: httpx>=0.28.1
Requires-Dist: faiss-cpu>=1.7.4
Requires-Dist: sentence-transformers>=2.2.0
Requires-Dist: torch<2.5,>=2.0.0
Requires-Dist: numpy>=1.24.0
Requires-Dist: pytest-asyncio>=1.3.0
Dynamic: license-file
